__init__.py
astro_science/__init__.py
astro_science/_version.py
astro_science/example.py
astro_science_ppt-0.0.1.dist-info/LICENSE
astro_science_ppt-0.0.1.dist-info/METADATA
astro_science_ppt-0.0.1.dist-info/WHEEL
astro_science_ppt-0.0.1.dist-info/top_level.txt
astro_science_ppt-0.0.1.dist-info/RECORD
